{"propertiesBar":{"properties":[{"name":"Sobre","expanded":true,"children":[]},{"name":"Cores","expanded":true,"children":[]},{"name":"Iniciar","expanded":true,"children":[]},{"name":"Exibição","expanded":true,"children":[{"name":"Tamanho da tela","expanded":false,"children":[]}]},{"name":"Avançado","expanded":false,"children":[]},{"name":"Configurações de compatibilidade","expanded":false,"children":[]},{"name":"Editor","expanded":true,"children":[]}],"scrollPosition":0},"openTabs":{"active":{"name":"eventos-f3","type":"eventSheet"},"open":[{"name":"fase1","type":"layout"},{"name":"fase2","type":"layout"},{"name":"fase3","type":"layout"},{"name":"eventos-base","type":"eventSheet"},{"name":"eventos-f1","type":"eventSheet"},{"name":"eventos-f2","type":"eventSheet"},{"name":"eventos-f3","type":"eventSheet"},{"name":"coletor.js","type":"projectFile"},{"name":"jacares","type":"eventSheet"},{"name":"serras","type":"eventSheet"},{"name":"zombies","type":"eventSheet"}]},"previewEffects":true,"previewBrowser":"default","pauseOnUnfocus":false,"projectBar":{"name":"<root>","children":[{"name":"Sombra","expanded":true,"children":[{"name":"Layouts","expanded":true,"children":[{"name":"fase1","expanded":true,"children":[]},{"name":"fase2","expanded":true,"children":[]},{"name":"fase3","expanded":true,"children":[]}]},{"name":"Folha de eventos","expanded":true,"children":[{"name":"eventos-base","expanded":true,"children":[]},{"name":"eventos-f1","expanded":true,"children":[]},{"name":"eventos-f2","expanded":true,"children":[]},{"name":"eventos-f3","expanded":true,"children":[]},{"name":"jacares","expanded":true,"children":[]},{"name":"serras","expanded":true,"children":[]},{"name":"zombies","expanded":true,"children":[]}]},{"name":"Scripts","expanded":true,"children":[{"name":"coletor.js","expanded":true,"children":[]}]},{"name":"Tipos de objeto","expanded":true,"children":[{"name":"Agua","expanded":true,"children":[]},{"name":"barra_energia","expanded":true,"children":[]},{"name":"base_solido","expanded":true,"children":[]},{"name":"Bloco","expanded":true,"children":[]},{"name":"btn_reiniciar","expanded":true,"children":[]},{"name":"btn_restart","expanded":true,"children":[]},{"name":"CAM","expanded":true,"children":[]},{"name":"Capivara","expanded":true,"children":[]},{"name":"carga","expanded":true,"children":[]},{"name":"debug","expanded":true,"children":[]},{"name":"FundoParqueAquatico","expanded":true,"children":[]},{"name":"FundoPinheiros","expanded":true,"children":[]},{"name":"GameOver","expanded":true,"children":[]},{"name":"Heart","expanded":true,"children":[]},{"name":"Jacare","expanded":true,"children":[]},{"name":"MosaicoHUD","expanded":true,"children":[]},{"name":"MosaicoPlataformas","expanded":true,"children":[]},{"name":"Mouse","expanded":true,"children":[]},{"name":"neve","expanded":true,"children":[]},{"name":"Partículas","expanded":true,"children":[]},{"name":"Portal","expanded":true,"children":[]},{"name":"rampa","expanded":true,"children":[]},{"name":"sensor_dir","expanded":true,"children":[]},{"name":"sensor_esq","expanded":true,"children":[]},{"name":"Serra","expanded":true,"children":[]},{"name":"Shuriken","expanded":true,"children":[]},{"name":"Teclado","expanded":true,"children":[]},{"name":"Tumulo","expanded":true,"children":[]},{"name":"txt_shuriken","expanded":true,"children":[]},{"name":"zombie","expanded":true,"children":[]},{"name":"zombieBerçario","expanded":true,"children":[]}]},{"name":"Famílias","expanded":true,"children":[]},{"name":"Linhas do tempo","expanded":true,"children":[{"name":"Atenuações","expanded":false,"children":[]},{"name":"Linha do tempo 1","expanded":true,"children":[]}]},{"name":"Fluxogramas","expanded":true,"children":[]},{"name":"Sons","expanded":true,"children":[]},{"name":"Música","expanded":true,"children":[]},{"name":"Vídeos","expanded":true,"children":[]},{"name":"Fontes","expanded":true,"children":[]},{"name":"Ícones & capturas de tela","expanded":false,"children":[{"name":"icon-128.png","expanded":true,"children":[]},{"name":"icon-16.png","expanded":true,"children":[]},{"name":"icon-256.png","expanded":true,"children":[]},{"name":"icon-32.png","expanded":true,"children":[]},{"name":"icon-512.png","expanded":true,"children":[]},{"name":"icon-64.png","expanded":true,"children":[]},{"name":"loading-logo.png","expanded":true,"children":[]}]},{"name":"Arquivos","expanded":true,"children":[]}]}]},"propertiesBarActiveObject":{"name":"instances","type":"array"}}